azyc/__init__.py
azyc/__main__.py
azyc/convert.py
azyc-0.5.0.dist-info/LICENSE
azyc-0.5.0.dist-info/METADATA
azyc-0.5.0.dist-info/WHEEL
azyc-0.5.0.dist-info/top_level.txt
azyc-0.5.0.dist-info/RECORD
