Metadata-Version: 2.1
Name: azyc
Version: 0.5.0
Summary: Helper to create large large deployment-parameters.json files from small yaml files
Home-page: https://github.com/claasd/azyc
Author: Claas Diederichs
Author-email: 
License: MIT
Platform: UNKNOWN
Classifier: Programming Language :: Python :: 3.6
Classifier: Programming Language :: Python :: 3.7
Classifier: Programming Language :: Python :: 3.8
Classifier: License :: OSI Approved :: MIT License
Classifier: Operating System :: OS Independent
Requires-Python: >=3.6
License-File: LICENSE
Requires-Dist: PyYaml
